{"id":"30e0afb6-c8fe-41ac-88a9-bee902c8fed9","name":"Staffordshire University","code":"S72","type":"university","ukprn":10006299,"accreditedProviderId":1531,"address":{"addressLine1":"Recruitment and Admissions, L600 Flaxman Building","addressLine2":"College Road","town":"Stoke-on-Trent","county":"Staffordshire","postcode":"ST4 2DE"},"location":{"latitude":53.0092019,"longitude":-2.1803515,"regionCode":"F"},"contact":{"website":"https://www.staffs.ac.uk/courses/subjects/education","email":"enquiries@staffs.ac.uk","telephone":"01782294400"},"accreditingProvider":true,"canSponsorSkilledWorkerVisa":false,"canSponsorStudentVisa":true}