{"id":"423f644c-b02d-4c22-b02c-b32d84c4ce9d","urn":137857,"ukprn":10036418,"name":"Quarrydale Academy","establishmentType":34,"establishmentGroup":10,"establishmentStatus":1,"establishmentPhase":4,"address":{"addressLine1":"Stoneyford Road","town":"Sutton-in-Ashfield","county":"Nottinghamshire","postcode":"NG17 2DU"},"location":{"latitude":53.1356241,"longitude":-1.266342,"regionCode":"E","localAuthorityCode":"891"},"contact":{"website":"http://www.quarrydale.notts.sch.uk/","telephone":"01623554178"},"minAge":11,"maxAge":18,"gender":3,"boarders":1,"officialSixthForm":1,"nurseryProvision":0,"childcareFacilities":0,"religiousCharacter":6,"admissionsPolicy":4,"schoolCapacity":1550,"totalPupils":1230,"totalBoys":599,"totalGirls":631,"specialClasses":2,"percentageFreeSchoolMeals":28.3,"trustSchool":5,"trustCode":4274,"furtherEducationType":0,"urbanRural":"C1","head":{"title":"Mr","firstName":"Tim","lastName":"Paling","jobTitle":"Headteacher"},"ofsted":{"rating":3,"lastInspectionDate":"2022-11-16T00:00:00.000Z"},"createdAt":"2023-09-06T13:20:38.824Z","updatedAt":"2023-09-06T13:20:38.824Z","trainingPartners":["ca188850-80bd-4872-882a-72692d4f8f3d"],"type":"school"}