{"id":"48de38ca-0f48-4bc0-98dc-3f7ba39ab183","name":"The Sheffield SCITT","code":"S97","type":"scitt","ukprn":10037587,"accreditedProviderId":5647,"address":{"addressLine1":"Notre Dame High School","addressLine2":"Fulwood Road","town":"Sheffield","county":"South Yorkshire","postcode":"S10 3BT"},"location":{"latitude":53.3727095,"longitude":-1.5171309,"regionCode":"D"},"contact":{"website":"https://www.sheffieldscitt.org.uk","email":"admin@sheffieldscitt.org.uk","telephone":"01142302536"},"isAccreditedProvider":true,"canSponsorSkilledWorkerVisa":false,"canSponsorStudentVisa":false}
