{"id":"b0052836-feca-4dda-9615-2576543792d4","urn":137425,"ukprn":10035113,"name":"Blessed Robert Widmerpool Catholic Primary and Nursery School","establishmentType":34,"establishmentGroup":10,"establishmentStatus":1,"establishmentPhase":2,"address":{"addressLine1":"Listowel Crescent","addressLine2":"Clifton","town":"Nottingham","county":"Nottinghamshire","postcode":"NG11 9BH"},"location":{"latitude":52.8976222,"longitude":-1.1784078,"regionCode":"E","localAuthorityCode":"892"},"contact":{"website":"brwacademy.com","telephone":"01159152392"},"minAge":3,"maxAge":11,"gender":3,"boarders":1,"officialSixthForm":0,"nurseryProvision":1,"childcareFacilities":0,"religiousCharacter":3,"admissionsPolicy":0,"schoolCapacity":240,"totalPupils":250,"totalBoys":129,"totalGirls":121,"specialClasses":2,"percentageFreeSchoolMeals":13.1,"trustSchool":3,"trustCode":4581,"schoolSponsorCode":17173,"furtherEducationType":0,"urbanRural":"B1","head":{"title":"Mrs","firstName":"Luisa","lastName":"Maylard-Mason","jobTitle":"Headteacher"},"ofsted":{"rating":1,"lastInspectionDate":"2022-03-23T00:00:00.000Z"},"createdAt":"2023-09-06T13:20:38.824Z","updatedAt":"2023-09-06T13:20:38.824Z","trainingPartners":["3a497939-7ced-4763-a749-6402e4f6546e"],"type":"school"}