{"id":"f55a2f9c-479a-46e3-922e-bb20e48a5219","name":"Wildern Partnership","code":"1WH","type":"scitt","ukprn":10033371,"address":{"addressLine1":"Wildern Partnership, Wildern School","addressLine2":"Wildern Lane","town":"Southampton","county":"Hampshire","postcode":"SO304EJ"},"location":{"latitude":50.9203157,"longitude":-1.3039747,"regionCode":"J"},"contact":{"website":"http://wildernpartnership.co.uk/","email":"scitt@wildernpartnership.co.uk","telephone":"01489779458"},"accreditingProvider":true,"canSponsorSkilledWorkerVisa":false,"canSponsorStudentVisa":false}